stwhas_api_client/__init__.py
stwhas_api_client/stwhasconsumptioncost.py
stwhas_api_client/stwhascostvalue.py
stwhas_api_client/stwhaseexdata.py
stwhas_api_client/stwhaseexvalue.py
stwhas_api_client/stwhasinterval.py
stwhas_api_client/stwhassmartmeterdata.py
stwhas_api_client/stwhassmartmetervalue.py
stwhas_api_client/stwhasunit.py
stwhas_python_api_client-1.0.11.dist-info/METADATA
stwhas_python_api_client-1.0.11.dist-info/WHEEL
stwhas_python_api_client-1.0.11.dist-info/top_level.txt
stwhas_python_api_client-1.0.11.dist-info/RECORD
