Metadata-Version: 2.1
Name: stwhas-python-api-client
Version: 1.0.11
Summary: Client for the API provided by Stadtwerk Haßfurt GmbH
Home-page: https://github.com/auenkind/stwhas-python-api-client
Author: David Neu
Author-email: mail@david-neu.de
Project-URL: Bug Tracker, https://github.com/auenkind/stwhas-python-api-client/issues
Project-URL: repository, https://github.com/auenkind/stwhas-python-api-client
Classifier: Programming Language :: Python :: 3
Classifier: License :: OSI Approved :: MIT License
Classifier: Operating System :: OS Independent
Requires-Python: >=3.8
Requires-Dist: requests
Requires-Dist: pytz
